djangotags/__init__.py
djangotags/apps.py
djangotags/urls.py
djangotags/contexts/TaggitTagListContext.py
djangotags/contexts/__init__.py
djangotags/migrations/__init__.py
djangotags/rest_api/__init__.py
djangotags/rest_api/urls.py
djangotags/rest_api/__pycache__/__init__.cpython-38.pyc
djangotags/rest_api/__pycache__/urls.cpython-38.pyc
djangotags/rest_api/serializers/TagSerializer.py
djangotags/rest_api/serializers/__init__.py
djangotags/rest_api/serializers/__pycache__/TagSerializer.cpython-38.pyc
djangotags/rest_api/serializers/__pycache__/__init__.cpython-38.pyc
djangotags/rest_api/viewsets/TagDestroyViewset.py
djangotags/rest_api/viewsets/TagListViewset.py
djangotags/rest_api/viewsets/TagRetrieveViewset.py
djangotags/rest_api/viewsets/TagUpdateViewset.py
djangotags/rest_api/viewsets/__init__.py
djangotags/rest_api/viewsets/__pycache__/TagDestroyViewset.cpython-38.pyc
djangotags/rest_api/viewsets/__pycache__/TagListViewset.cpython-38.pyc
djangotags/rest_api/viewsets/__pycache__/TagRetrieveViewset.cpython-38.pyc
djangotags/rest_api/viewsets/__pycache__/TagUpdateViewset.cpython-38.pyc
djangotags/rest_api/viewsets/__pycache__/__init__.cpython-38.pyc
djangotags/templates/djangoadmin/djangotags/taggit_tag_detail_view.html
djangotags/views/TaggitTagDetailView.py
djangotags/views/__init__.py
djangotags/views/__pycache__/TaggitTagDetailView.cpython-38.pyc
djangotags/views/__pycache__/__init__.cpython-38.pyc
djangotags-2.2.2.dist-info/License
djangotags-2.2.2.dist-info/METADATA
djangotags-2.2.2.dist-info/WHEEL
djangotags-2.2.2.dist-info/top_level.txt
djangotags-2.2.2.dist-info/RECORD
